{
  "date": "2026-05-05",
  "pick_dia": null,
  "picks_suscripcion": [
    {
      "slug": "deportivo-riestra-vs-gremio-copa-sudamericana-2026-05-05",
      "matchup": "Deportivo Riestra vs Grêmio",
      "league": "Copa Sudamericana",
      "tipo": "pick_suscripcion",
      "market": "Apuesta sin empate: Grêmio",
      "prob_adjusted": 61.6,
      "value_score": null,
      "confidence_factor": 0.97,
      "ev_adjusted": 24.6,
      "bk_odds": 2.023
    },
    {
      "slug": "detroit-pistons-vs-cleveland-cavaliers-nba-2026-05-05",
      "matchup": "Detroit Pistons vs Cleveland Cavaliers",
      "league": "NBA",
      "tipo": "pick_gratuito",
      "market": "Detroit Pistons",
      "prob_adjusted": 62.0,
      "value_score": null,
      "confidence_factor": 1.0,
      "ev_adjusted": 8.5,
      "bk_odds": 1.75
    }
  ],
  "pick_gratuito": {
    "slug": "detroit-pistons-vs-cleveland-cavaliers-nba-2026-05-05",
    "matchup": "Detroit Pistons vs Cleveland Cavaliers",
    "league": "NBA",
    "tipo": "pick_gratuito",
    "market": "Detroit Pistons",
    "prob_adjusted": 62.0,
    "value_score": null,
    "confidence_factor": 1.0,
    "ev_adjusted": 8.5,
    "bk_odds": 1.75
  },
  "pick_exploratorio": null,
  "analisis_goles": []
}