{
  "date": "2026-05-09",
  "pick_dia": null,
  "picks_suscripcion": [
    {
      "slug": "cagliari-vs-udinese-serie-a-2026-05-09",
      "matchup": "Cagliari vs Udinese",
      "league": "Serie A",
      "tipo": "pick_suscripcion",
      "market": "Apuesta sin empate: Udinese",
      "prob_adjusted": 64.8,
      "value_score": null,
      "confidence_factor": 1.0,
      "ev_adjusted": 28.5,
      "bk_odds": 1.984,
      "cuota_referencia": 1.984,
      "cuota_betplay_estimada": 1.79,
      "ev_referencia": 28.5,
      "ev_betplay_estimado": 16.0,
      "mercado_referencia": "Pinnacle/Bet365 (europeo)",
      "disclaimer": "Cuota Betplay estimada con descuento del 10% promedio. Verifica antes de apostar."
    },
    {
      "slug": "kocaelispor-vs-fatih-karagumruk-super-lig-2026-05-09",
      "matchup": "Kocaelispor vs Fatih Karagümrük",
      "league": "Super Lig",
      "tipo": "pick_suscripcion",
      "market": "Apuesta sin empate: Kocaelispor",
      "prob_adjusted": 75.0,
      "value_score": null,
      "confidence_factor": 0.97,
      "ev_adjusted": 29.7,
      "bk_odds": 1.73,
      "cuota_referencia": 1.73,
      "cuota_betplay_estimada": 1.56,
      "ev_referencia": 29.7,
      "ev_betplay_estimado": 17.0,
      "mercado_referencia": "Pinnacle/Bet365 (europeo)",
      "disclaimer": "Cuota Betplay estimada con descuento del 10% promedio. Verifica antes de apostar."
    },
    {
      "slug": "eyupspor-vs-caykur-rizespor-super-lig-2026-05-09",
      "matchup": "Eyupspor vs Caykur Rizespor",
      "league": "Super Lig",
      "tipo": "pick_gratuito",
      "market": "Doble oportunidad: Caykur Rizespor",
      "prob_adjusted": 75.5,
      "value_score": null,
      "confidence_factor": 0.97,
      "ev_adjusted": 29.7,
      "bk_odds": 1.719,
      "cuota_referencia": 1.719,
      "cuota_betplay_estimada": 1.55,
      "ev_referencia": 29.7,
      "ev_betplay_estimado": 17.0,
      "mercado_referencia": "Pinnacle/Bet365 (europeo)",
      "disclaimer": "Cuota Betplay estimada con descuento del 10% promedio. Verifica antes de apostar."
    },
    {
      "slug": "alanyaspor-vs-kayserispor-super-lig-2026-05-09",
      "matchup": "Alanyaspor vs Kayserispor",
      "league": "Super Lig",
      "tipo": "pick_suscripcion",
      "market": "Apuesta sin empate: Alanyaspor",
      "prob_adjusted": 73.4,
      "value_score": null,
      "confidence_factor": 0.97,
      "ev_adjusted": 28.1,
      "bk_odds": 1.745,
      "cuota_referencia": 1.745,
      "cuota_betplay_estimada": 1.57,
      "ev_referencia": 28.1,
      "ev_betplay_estimado": 15.2,
      "mercado_referencia": "Pinnacle/Bet365 (europeo)",
      "disclaimer": "Cuota Betplay estimada con descuento del 10% promedio. Verifica antes de apostar."
    }
  ],
  "pick_gratuito": {
    "slug": "eyupspor-vs-caykur-rizespor-super-lig-2026-05-09",
    "matchup": "Eyupspor vs Caykur Rizespor",
    "league": "Super Lig",
    "tipo": "pick_gratuito",
    "market": "Doble oportunidad: Caykur Rizespor",
    "prob_adjusted": 75.5,
    "value_score": null,
    "confidence_factor": 0.97,
    "ev_adjusted": 29.7,
    "bk_odds": 1.719,
    "cuota_referencia": 1.719,
    "cuota_betplay_estimada": 1.55,
    "ev_referencia": 29.7,
    "ev_betplay_estimado": 17.0,
    "mercado_referencia": "Pinnacle/Bet365 (europeo)",
    "disclaimer": "Cuota Betplay estimada con descuento del 10% promedio. Verifica antes de apostar."
  },
  "pick_exploratorio": null,
  "analisis_goles": []
}